circuitpython_uplot/__init__.py
circuitpython_uplot/bar.py
circuitpython_uplot/cartesian.py
circuitpython_uplot/fillbetween.py
circuitpython_uplot/icons.py
circuitpython_uplot/logging.py
circuitpython_uplot/map.py
circuitpython_uplot/pie.py
circuitpython_uplot/plot.py
circuitpython_uplot/polar.py
circuitpython_uplot/scatter.py
circuitpython_uplot/shade.py
circuitpython_uplot/svg.py
circuitpython_uplot-2.0.0.dist-info/LICENSE
circuitpython_uplot-2.0.0.dist-info/METADATA
circuitpython_uplot-2.0.0.dist-info/WHEEL
circuitpython_uplot-2.0.0.dist-info/top_level.txt
circuitpython_uplot-2.0.0.dist-info/RECORD
