Metadata-Version: 2.1
Name: circuitpython-uplot
Version: 2.0.0
Summary: framework to display different plots in displayio. similar to widget
Author-email: JDM <uplot@mailmeto.mozmail.com>
License: MIT
Project-URL: Homepage, https://github.com/jposada202020/CircuitPython_uplot
Keywords: circuitpython,uplot,microplot,bar,stackplot,fillbetween,piechart,scatter,line,displayio,graphics,library,ulab,svg,widget,graph,graphing,chart,charts,plotting,plot,plotter
Classifier: Intended Audience :: Developers
Classifier: Topic :: Software Development :: Libraries
Classifier: Topic :: Software Development :: Embedded Systems
Classifier: Topic :: System :: Hardware
Classifier: License :: OSI Approved :: MIT License
Classifier: Programming Language :: Python :: 3
License-File: LICENSE
Requires-Dist: Adafruit-Blinka
Requires-Dist: typing-extensions~=4.0
Provides-Extra: optional
